zonebuilder-1.0.1.dist-info/METADATA
zonebuilder-1.0.1.dist-info/WHEEL
zonebuilder/__init__.py
zonebuilder/zonebuilder.cpython-38-darwin.so
zonebuilder-1.0.1.dist-info/RECORD
