Metadata-Version: 2.1
Name: zonebuilder
Version: 1.0.1
Summary: Python package for creating zoning systems
Author: Pushkar Kopparla
Author-email: pushkarkopparla@gmail.com
Maintainer-email: Dustin Carlino <dabreegster@gmail.com>, Robin Lovelace <zonebuildersr@gmail.com>
License: GNU Affero General Public License v3
Project-URL: Homepage, https://github.com/zonebuilders/zonebuilder-py
